{
  "project_info": {
    "project_number": "857810816166",
    "firebase_url": "https://mymap-d96b0.firebaseio.com",
    "project_id": "mymap-d96b0",
    "storage_bucket": "mymap-d96b0.appspot.com"
  },
  "client": [
    {
      "client_info": {
        "mobilesdk_app_id": "1:857810816166:android:112163213371e8b389b867",
        "android_client_info": {
          "package_name": "com.example.mymap"
        }
      },
      "oauth_client": [
        {
          "client_id": "857810816166-u9fj1upsqqvhjdefjd15hej3i5qhvhje.apps.googleusercontent.com",
          "client_type": 1,
          "android_info": {
            "package_name": "com.example.mymap",
            "certificate_hash": "11ad050c1db387609847eaa02e8899fe23b4b181"
          }
        },
        {
          "client_id": "857810816166-4rik70k5ca3sljtgvlqvu3p2qf5lc1jj.apps.googleusercontent.com",
          "client_type": 3
        }
      ],
      "api_key": [
        {
          "current_key": "AIzaSyCFSGiYFx_tasj_x2MJix5Uryse5S6pNQw"
        }
      ],
      "services": {
        "appinvite_service": {
          "other_platform_oauth_client": [
            {
              "client_id": "857810816166-4rik70k5ca3sljtgvlqvu3p2qf5lc1jj.apps.googleusercontent.com",
              "client_type": 3
            }
          ]
        }
      }
    }
  ],
  "configuration_version": "1"
}